whitefuck/__init__.py
whitefuck/__main__.py
whitefuck-1.0.0.dist-info/LICENSE
whitefuck-1.0.0.dist-info/METADATA
whitefuck-1.0.0.dist-info/WHEEL
whitefuck-1.0.0.dist-info/entry_points.txt
whitefuck-1.0.0.dist-info/top_level.txt
whitefuck-1.0.0.dist-info/RECORD
