Metadata-Version: 2.1
Name: whitefuck
Version: 1.0.0
Summary: (Whitespace + Brainfuck) / 2 = Whitefuck
Home-page: https://github.com/sevenc-nanashi/sembed
Author: sevenc_nanashi
License: UNKNOWN
Platform: UNKNOWN
Classifier: Programming Language :: Python :: 3.8
Classifier: License :: OSI Approved :: MIT License
Classifier: Operating System :: OS Independent
